dataprocess/__init__.py
dataprocess/dataprocessing.py
etl_dataprocess-0.2.7.dist-info/licenses/LICENSE
etl_dataprocess-0.2.7.dist-info/METADATA
etl_dataprocess-0.2.7.dist-info/WHEEL
etl_dataprocess-0.2.7.dist-info/top_level.txt
etl_dataprocess-0.2.7.dist-info/RECORD
